setup.py
base/__init__.py
base/Queue_Multi_thread/Muti_thread.py
base/Queue_Multi_thread/__init__.py
base/Store/ElasticSearch.py
base/Store/FactoryItems.py
base/Store/Items.py
base/Store/__init__.py
base/spider/ItemLoader.py
base/spider/Spider.py
base/spider/__init__.py
base/tools/__init__.py
base/tools/class_to_dict.py
base/tools/config_trans_dic.py
base/tools/log.py
base/tools/var_to_dict.py
project/__init__.py
project/items/__init__.py
project/scrapy/__init__.py
scrapy_allen.egg-info/PKG-INFO
scrapy_allen.egg-info/SOURCES.txt
scrapy_allen.egg-info/dependency_links.txt
scrapy_allen.egg-info/requires.txt
scrapy_allen.egg-info/top_level.txt