Metadata-Version: 1.0
Name: scrapy-allen
Version: 0.1.0
Summary: 模块描述
Home-page: UNKNOWN
Author: Shu Huang
Author-email: fengyeyouni@163.com
License: MIT Licence
Keywords: pip,scrapy,elasticsearch
Platform: any
